LICENSE
README.md
setup.cfg
setup.py
blog/__init__.py
blog/__main__.py
blog/errors.py
blog/install.py
blog/records.py
blog/rest.py
blog/seo.py
blog/service.py
blog/sitemap.py
blog/definitions/category.json
blog/definitions/category_locale.json
blog/definitions/comment.json
blog/definitions/media.json
blog/definitions/post.json
blog/definitions/post_category.json
blog/definitions/post_raw.json
blog/definitions/post_tag.json
blog/media/__init__.py
blog/media/s3.py
blog/translations/en-CA.json
blog/translations/en-US.json
blog/translations/fr-CA.json
blog_oc.egg-info/PKG-INFO
blog_oc.egg-info/SOURCES.txt
blog_oc.egg-info/dependency_links.txt
blog_oc.egg-info/entry_points.txt
blog_oc.egg-info/requires.txt
blog_oc.egg-info/top_level.txt
blog_oc.egg-info/zip-safe