Metadata-Version: 2.1
Name: blog-oc
Version: 0.2.0
Summary: Blog contains a service to manage blog posts and comments associated
Home-page: https://ouroboroscoding.com/body/blog
Author: Chris Nasr - Ouroboros Coding Inc.
Author-email: chris@ouroboroscoding.com
License: Custom
Project-URL: Documentation, https://ouroboroscoding.com/body/blog
Project-URL: Source, https://github.com/ouroboroscoding/blog
Project-URL: Tracker, https://github.com/ouroboroscoding/blog/issues
Keywords: rest,microservices
Platform: UNKNOWN
Requires-Python: >=3.10
License-File: LICENSE
